mayavoz-0.0.1-py3.8-nspkg.pth
mayavoz/inference.py
mayavoz/loss.py
mayavoz/version.py
mayavoz/cli/train.py
mayavoz/cli/train_config/config.yaml
mayavoz/cli/train_config/dataset/MS-SNSD.yaml
mayavoz/cli/train_config/dataset/Valentini.yaml
mayavoz/cli/train_config/dataset/Vctk_local.yaml
mayavoz/cli/train_config/hyperparameters/default.yaml
mayavoz/cli/train_config/mlflow/experiment.yaml
mayavoz/cli/train_config/model/DCCRN.yaml
mayavoz/cli/train_config/model/Demucs.yaml
mayavoz/cli/train_config/model/WaveUnet.yaml
mayavoz/cli/train_config/optimizer/Adam.yaml
mayavoz/cli/train_config/trainer/default.yaml
mayavoz/cli/train_config/trainer/fastrun_dev.yaml
mayavoz/data/__init__.py
mayavoz/data/dataset.py
mayavoz/data/fileprocessor.py
mayavoz/models/__init__.py
mayavoz/models/dccrn.py
mayavoz/models/demucs.py
mayavoz/models/model.py
mayavoz/models/waveunet.py
mayavoz/models/complexnn/__init__.py
mayavoz/models/complexnn/conv.py
mayavoz/models/complexnn/rnn.py
mayavoz/models/complexnn/utils.py
mayavoz/utils/__init__.py
mayavoz/utils/config.py
mayavoz/utils/io.py
mayavoz/utils/random.py
mayavoz/utils/transforms.py
mayavoz/utils/utils.py
mayavoz-0.0.1.data/data/requirements.txt
mayavoz-0.0.1.data/data/_/version.txt
mayavoz-0.0.1.dist-info/LICENSE
mayavoz-0.0.1.dist-info/METADATA
mayavoz-0.0.1.dist-info/WHEEL
mayavoz-0.0.1.dist-info/entry_points.txt
mayavoz-0.0.1.dist-info/namespace_packages.txt
mayavoz-0.0.1.dist-info/top_level.txt
mayavoz-0.0.1.dist-info/RECORD
