Metadata-Version: 2.1
Name: mayavoz
Version: 0.0.1
Summary: Deep learning toolkit for speech enhancement
Home-page: 
Author: Shahul Es
Author-email: shahules786@gmail.com
License: mit
Platform: Linux
Platform: Mac
Classifier: Development Status :: 4 - Beta
Classifier: Intended Audience :: Science/Research
Classifier: License :: OSI Approved :: MIT License
Classifier: Natural Language :: English
Classifier: Programming Language :: Python :: 3.7
Classifier: Programming Language :: Python :: 3.8
Classifier: Topic :: Scientific/Engineering
Requires-Python: >=3.8
License-File: LICENSE
Requires-Dist: boto3 (>=1.24.86)
Requires-Dist: huggingface-hub (>=0.10.0)
Requires-Dist: hydra-core (>=1.2.0)
Requires-Dist: joblib (>=1.2.0)
Requires-Dist: librosa (>=0.9.2)
Requires-Dist: mlflow (>=1.28.0)
Requires-Dist: numpy (>=1.23.3)
Requires-Dist: pesq (==0.0.4)
Requires-Dist: protobuf (>=3.19.6)
Requires-Dist: pystoi (==0.3.3)
Requires-Dist: pytest-lazy-fixture (>=0.6.3)
Requires-Dist: pytorch-lightning (>=1.7.7)
Requires-Dist: scikit-learn (>=1.1.2)
Requires-Dist: scipy (>=1.9.1)
Requires-Dist: soundfile (>=0.11.0)
Requires-Dist: torch (>=1.12.1)
Requires-Dist: torch-audiomentations (==0.11.0)
Requires-Dist: torchaudio (>=0.12.1)
Requires-Dist: tqdm (>=4.64.1)
Provides-Extra: cli
Requires-Dist: hydra-core (<=1.2,>=1.1) ; extra == 'cli'
Provides-Extra: dev
Requires-Dist: pre-commit (>=2.20.0) ; extra == 'dev'
Requires-Dist: black (>=22.8.0) ; extra == 'dev'
Requires-Dist: flake8 (>=5.0.4) ; extra == 'dev'
Provides-Extra: testing
Requires-Dist: pytest (>=7.1.3) ; extra == 'testing'
Requires-Dist: pytest-cov (>=4.0.0) ; extra == 'testing'
